livedesktop.py
setup.py
livedesktop.egg-info/PKG-INFO
livedesktop.egg-info/SOURCES.txt
livedesktop.egg-info/dependency_links.txt
livedesktop.egg-info/entry_points.txt
livedesktop.egg-info/requires.txt
livedesktop.egg-info/top_level.txt