Metadata-Version: 1.0
Name: livedesktop
Version: 0.1.0
Summary: Bring your desktop wallpaper alive!
Home-page: https://github.com/olivopaolo/livedesktop
Author: Paolo Olivo
Author-email: olivopaolo@tiscali.it
License: GPLv3
Platform: UNKNOWN
Classifier: Development Status :: 3 - Alpha
Classifier: Environment :: Console
Classifier: Intended Audience :: End Users/Desktop
Classifier: License :: OSI Approved :: GNU General Public License v3 (GPLv3)
Classifier: Natural Language :: English
Classifier: Operating System :: MacOS :: MacOS X
Classifier: Operating System :: Microsoft :: Windows
Classifier: Operating System :: POSIX :: Linux
Classifier: Programming Language :: Python
Classifier: Topic :: Scientific/Engineering :: Human Machine Interfaces
Classifier: Topic :: Utilities
